{
  "sections": {
    "article": {
      "type": "article-template",
      "blocks": {
        "4719c871-5612-465a-a169-c71ed12eb496": {
          "type": "search",
          "disabled": true,
          "settings": {
            "title": ""
          }
        },
        "d93736f3-6af7-4a55-82fb-1b7116d51b1f": {
          "type": "products",
          "settings": {
            "title": "Popular Products",
            "sidebar_products": "velo-electrique",
            "num_of_products": "3",
            "side_all_products": false,
            "btn_txt": "View All",
            "side_prod_opt": "list"
          }
        },
        "f250fe59-2ef9-4aad-9c70-6bd81219d4ff": {
          "type": "menu",
          "disabled": true,
          "settings": {
            "title": "Categories",
            "side_categories": ""
          }
        },
        "2ba1fb83-1b45-493e-8110-40ca2ed8ec8d": {
          "type": "rposts",
          "settings": {
            "title": "Recent Posts",
            "count": 5
          }
        },
        "b6606bd2-f599-49ce-a1f3-3935f06a6d84": {
          "type": "image_bnr",
          "disabled": true,
          "settings": {
            "side_bnr_link": ""
          }
        },
        "dcbc5b35-6d4e-4478-b6e7-9a44194f4d93": {
          "type": "image_bnr",
          "disabled": true,
          "settings": {
            "side_bnr_link": ""
          }
        },
        "f1c74a1f-502e-43d4-a4d1-8920146383ac": {
          "type": "tags",
          "disabled": true,
          "settings": {
            "title": "Tags"
          }
        }
      },
      "block_order": [
        "4719c871-5612-465a-a169-c71ed12eb496",
        "d93736f3-6af7-4a55-82fb-1b7116d51b1f",
        "f250fe59-2ef9-4aad-9c70-6bd81219d4ff",
        "2ba1fb83-1b45-493e-8110-40ca2ed8ec8d",
        "b6606bd2-f599-49ce-a1f3-3935f06a6d84",
        "dcbc5b35-6d4e-4478-b6e7-9a44194f4d93",
        "f1c74a1f-502e-43d4-a4d1-8920146383ac"
      ],
      "settings": {
        "top-offeset": "default",
        "section_width": false,
        "sidebar_position": "left",
        "text_align": "text-left",
        "blogfs": 25,
        "blogfsm": 18,
        "blogtf": "font2",
        "blogtw": "fw-600",
        "featured-img": true,
        "blog_show_author": true,
        "blog_show_date": true,
        "show_share_buttons": true,
        "show_rlpr": true,
        "related_title": "Related Products",
        "related_sub_title": "",
        "grid": 4,
        "tablet-grid": 3,
        "mobile-grid": 2,
        "rpauto": false,
        "auto_speed": 5
      }
    },
    "6b041c72-f0ec-4bcb-939c-572f18340404": {
      "type": "section-space",
      "settings": {
        "sdesk": 30,
        "mdesk": 15,
        "color_bg": "#ffffff"
      }
    },
    "22c03e54-e03e-4ffb-97a6-664a64e7d103": {
      "type": "section-space",
      "settings": {
        "sdesk": 30,
        "mdesk": 15,
        "color_bg": "#ffffff"
      }
    }
  },
  "order": [
    "article",
    "6b041c72-f0ec-4bcb-939c-572f18340404",
    "22c03e54-e03e-4ffb-97a6-664a64e7d103"
  ]
}
