{
  "sections": {
    "slideshow": {
      "type": "slideshow",
      "blocks": {
        "1561726660568-0": {
          "type": "image",
          "settings": {
            "image": "shopify:\/\/shop_images\/EC_1_Banner_1_a.jpg",
            "imagem": "shopify:\/\/shop_images\/EC_1_Banner_Vertical_version.jpg",
            "ialign": "center_center",
            "hd1": "EC 1",
            "pcl": "#ffffff",
            "title": "Apportez une vie idéale à l'Iran !",
            "tcl": "#ffffff",
            "hd3": "",
            "hideh3": true,
            "cl": "#ffffff",
            "btn": "Acheter maintenant &nbsp >",
            "link": "shopify:\/\/products\/ec-1",
            "btn1window": false,
            "btn-style": "btn",
            "display_btn": false,
            "btn2": "Shop Now",
            "link2": "shopify:\/\/collections",
            "btn2window": false,
            "btn-style1": "btn1",
            "contwd": 1300,
            "text-left": true,
            "txtpos": "f-aic-md f-jcs-md",
            "txtposm": "f-ais f-jcs"
          }
        },
        "208504ac-576d-4468-85f2-307d5444445e": {
          "type": "image",
          "settings": {
            "image": "shopify:\/\/shop_images\/Banner_0815_07de7446-e5a4-4023-8e55-165f4f208161.jpg",
            "imagem": "shopify:\/\/shop_images\/a21.jpg",
            "ialign": "center_center",
            "hd1": "EC 1-ST",
            "pcl": "#000000",
            "title": "Apportez une vie idéale à l'Iran !",
            "tcl": "#3b3a3a",
            "hd3": "",
            "hideh3": true,
            "cl": "#ffffff",
            "btn": "Acheter maintenant &nbsp >",
            "link": "shopify:\/\/products\/ec-1-st",
            "btn1window": false,
            "btn-style": "btn",
            "display_btn": false,
            "btn2": "Shop Now",
            "link2": "shopify:\/\/collections",
            "btn2window": false,
            "btn-style1": "btn1",
            "contwd": 1300,
            "text-left": true,
            "txtpos": "f-aic-md f-jcs-md",
            "txtposm": "f-ais f-jcs"
          }
        }
      },
      "block_order": [
        "1561726660568-0",
        "208504ac-576d-4468-85f2-307d5444445e"
      ],
      "settings": {
        "top-offeset": "none",
        "ht": "1",
        "htd": 700,
        "htt": 550,
        "htm": 400,
        "section_width": false,
        "box-width": 1500,
        "isovr": false,
        "obg": "#111111",
        "oopt": 0.5,
        "style": "hbstyle",
        "pfs": 30,
        "pff": "ft1",
        "pfw": "400",
        "plh": 1.2,
        "pmb": 0,
        "bfs": 72,
        "bff": "ft2",
        "bfw": "700",
        "blh": 1.1,
        "bmb": 20,
        "dfs": 16,
        "dff": "ft1",
        "dfw": "400",
        "dlh": 1.2,
        "dmb": 25,
        "txtanimation": true,
        "anim": "st1",
        "btn-size": "btn-md",
        "btn-sizem": "mob-btn-sm",
        "isbox": false,
        "isboxm": false,
        "tbg": "#ffffff",
        "opt": 0.9,
        "brad": 0,
        "autoplay": true,
        "speed": 7,
        "arrow": false,
        "arrowc": "#444444",
        "dot": true,
        "dots": "#000000",
        "snow_effect": false,
        "snow_style": "style1"
      }
    },
    "583b741b-600f-49b4-9c12-175b587241ee": {
      "type": "products-slider-full",
      "blocks": {
        "49c3920c-4c72-4966-97a0-17f141bf1e62": {
          "type": "slide",
          "settings": {
            "product": "ec-1",
            "product_image": "shopify:\/\/shop_images\/cdaa4012fb613cdf2d9036a9987dbd0d.png",
            "info": "Répondre à vos besoins pour les trajets domicile-travail"
          }
        },
        "aced053b-8c7e-443c-ba77-07bf8bef930e": {
          "type": "slide",
          "settings": {
            "product": "ec-1-st",
            "product_image": "shopify:\/\/shop_images\/c1d84cdd17073b62f80ac3d3d4718328.png",
            "info": "Conception en escalier : Rouler avec facilité"
          }
        },
        "265ae58e-bbd5-431e-950a-654097cb3d2c": {
          "type": "slide",
          "settings": {
            "product": "ec-1",
            "product_image": "shopify:\/\/shop_images\/4c38906b2b9284a369c7d610f6e1c17f.png",
            "info": "Répondre à vos besoins pour les trajets domicile-travail"
          }
        },
        "f480f755-ce5b-49ba-93bd-4d6b4ea96954": {
          "type": "slide",
          "settings": {
            "product": "ec-1-st",
            "product_image": "shopify:\/\/shop_images\/b32509eed7cb08b46e6ff624f8b8370e.png",
            "info": "Conception en escalier : Rouler avec facilité"
          }
        },
        "74434e2d-7316-4cea-a46d-2fe1337dab28": {
          "type": "slide",
          "settings": {
            "product": "ec-1",
            "product_image": "shopify:\/\/shop_images\/453d27d1bcbe9b2b22b05a976ef6d8cb.png",
            "info": "Répondre à vos besoins pour les trajets domicile-travail"
          }
        },
        "f8ffd36a-8915-47a9-930d-e2ad87fcd760": {
          "type": "slide",
          "settings": {
            "product": "ec-1-st",
            "product_image": "shopify:\/\/shop_images\/697ef5c2066bf49f4df46a227b1a93c1.png",
            "info": "Conception en escalier : Rouler avec facilité"
          }
        }
      },
      "block_order": [
        "49c3920c-4c72-4966-97a0-17f141bf1e62",
        "aced053b-8c7e-443c-ba77-07bf8bef930e",
        "265ae58e-bbd5-431e-950a-654097cb3d2c",
        "f480f755-ce5b-49ba-93bd-4d6b4ea96954",
        "74434e2d-7316-4cea-a46d-2fe1337dab28",
        "f8ffd36a-8915-47a9-930d-e2ad87fcd760"
      ],
      "settings": {
        "top_padding": "large",
        "bottom_padding": "default",
        "title": "Tous les modèles HEYBIKE",
        "btn_Text": "Acheter maintenant",
        "bg_color": "#f3f5f9"
      }
    },
    "6466a547-b260-459b-b173-ee05a2e100ae": {
      "type": "logo-slider",
      "blocks": {
        "6029181d-3f62-44e0-aa3e-438b6cddb31c": {
          "type": "slide",
          "settings": {
            "text_main": "\"The HeyBike Mars is a special type of fat tire e-bike that folds down for easier transportation, meaning you can take that ride-everywhere fun on the go with you.\"",
            "text_sub": "- ELECTREK",
            "logo_image": "shopify:\/\/shop_images\/cropped-electrek-logo11.webp"
          }
        },
        "bfd88edc-65df-4713-b474-231d6eb30b82": {
          "type": "slide",
          "settings": {
            "text_main": "\"The Heybike Mars hits a good price point and is a lot of fun to ride.\"",
            "text_sub": "- MSN",
            "logo_image": "shopify:\/\/shop_images\/images.png"
          }
        },
        "4154eb24-d1e7-4988-890f-30696b81b6ea": {
          "type": "slide",
          "settings": {
            "text_main": "\"When it comes to solid, folding e-bikes, HeyBike has got game, with the manufacturer presenting us with a wide range of fat-tire wheelers.\"",
            "text_sub": "- AUTOEVOLUTION",
            "logo_image": "shopify:\/\/shop_images\/AU.png"
          }
        },
        "32c33951-7d78-4c30-9e61-72ec75ab3884": {
          "type": "slide",
          "settings": {
            "text_main": "\"The Heybike Cityrun stands out for safety and security features, and even has a place to put your water bottle. It's the perfect e-bike for commuting.\"",
            "text_sub": "- ZDNET",
            "logo_image": "shopify:\/\/shop_images\/ZDNet-logo-347F1C3C61-seeklogo.com.png"
          }
        },
        "707889c1-1ed2-47d6-b2ea-e60f9ad69530": {
          "type": "slide",
          "settings": {
            "text_main": "\"The Brawn from Heybike is a motorcycle inspired off-road beast.\"",
            "text_sub": "- electrifiedreviews",
            "logo_image": "shopify:\/\/shop_images\/logo.png"
          }
        },
        "4758eb01-b94b-42b2-b933-de9ec51b2bd0": {
          "type": "slide",
          "settings": {
            "text_main": "MARS is a good choice for those people who want to use their bikes in multiple scenarios, like commuting and outdoor off-road.",
            "text_sub": "- Techtimes",
            "logo_image": "shopify:\/\/shop_images\/6fb53c51539b47559cf0d122a832cf63.png"
          }
        }
      },
      "block_order": [
        "6029181d-3f62-44e0-aa3e-438b6cddb31c",
        "bfd88edc-65df-4713-b474-231d6eb30b82",
        "4154eb24-d1e7-4988-890f-30696b81b6ea",
        "32c33951-7d78-4c30-9e61-72ec75ab3884",
        "707889c1-1ed2-47d6-b2ea-e60f9ad69530",
        "4758eb01-b94b-42b2-b933-de9ec51b2bd0"
      ],
      "settings": {
        "top_padding": "large",
        "bottom_padding": "small",
        "style": "default",
        "bg_img": "shopify:\/\/shop_images\/2.png",
        "bg_color": "",
        "text_color": "#ffffff"
      }
    },
    "8ac0dd31-ebc0-46e2-867c-a7d6e2e0fd90": {
      "type": "data-statistics",
      "blocks": {
        "55af95fe-1f67-44a9-922b-0a20b4838325": {
          "type": "slide",
          "settings": {
            "text_main": "2,824,160",
            "text_suf": "km",
            "text_sub": "Distance totale Riden"
          }
        },
        "2cec7d8f-443d-475d-82d9-58b68117bc6d": {
          "type": "slide",
          "settings": {
            "text_main": "80000",
            "text_suf": "+",
            "text_sub": "Cavaliers actifs"
          }
        },
        "3b0e13f5-a095-46d4-afa9-e33dfc671812": {
          "type": "slide",
          "settings": {
            "text_main": "4,531,101",
            "text_suf": "kg",
            "text_sub": "Total des émissions de CO₂ économisées"
          }
        },
        "752b2092-7e2b-4a37-b195-38804c6a344e": {
          "type": "slide",
          "settings": {
            "text_main": "987,865",
            "text_suf": "pcs",
            "text_sub": "Équivalent arbres plantés"
          }
        }
      },
      "block_order": [
        "55af95fe-1f67-44a9-922b-0a20b4838325",
        "2cec7d8f-443d-475d-82d9-58b68117bc6d",
        "3b0e13f5-a095-46d4-afa9-e33dfc671812",
        "752b2092-7e2b-4a37-b195-38804c6a344e"
      ],
      "custom_css": [

      ],
      "settings": {
        "top_padding": "none",
        "bottom_padding": "large",
        "bg_color": "#f3f5f9",
        "title": "Passer au vert avec Heybike",
        "image": "shopify:\/\/shop_images\/7d1092826674963ad143e87bf6fb8dcd.jpg"
      }
    },
    "9097e021-5397-4a21-8d22-e6f121fbda8f": {
      "type": "image-text",
      "settings": {
        "top_padding": "large",
        "bottom_padding": "default",
        "bg_color": "#000000",
        "bg_img": "shopify:\/\/shop_images\/C.jpg",
        "text_main": "Trouver un concessionnaire près de chez vous",
        "text_sub": "Essai et achat direct",
        "text_btn": "Lire la suite",
        "url": "shopify:\/\/pages\/trouver-une-affaire"
      }
    },
    "a2d3fa24-4809-40c0-b63d-a720d6b02f2c": {
      "type": "multiple-image-text",
      "blocks": {
        "16e18420-5cfa-45d6-a2b4-a4157ffc0f22": {
          "type": "image",
          "settings": {
            "slide_w": "w-2\/3",
            "bg_color": "",
            "bg_img": "shopify:\/\/shop_images\/Blog.jpg",
            "bg_img_mb": "shopify:\/\/shop_images\/Blog.jpg",
            "text_main": "Heybike Deals - Prévente EC 1 et EC 1-ST : Découvrez l'avenir du cyclisme.",
            "text_sub": "Nous sommes heureux d'annoncer la prévente des EC 1 et EC 1-ST, les nouveaux modèles de Heybike.",
            "img_link": "shopify:\/\/blogs\/blog-heybike\/heybike-deals-evenement-de-prevente-ec-1-et-ec-1-st-de-heybike-decouvrez-lavenir-du-cyclisme"
          }
        },
        "61279fbb-db0a-4969-b5f8-ca73202edf62": {
          "type": "image",
          "settings": {
            "slide_w": "w-1\/3",
            "bg_color": "",
            "bg_img": "shopify:\/\/shop_images\/lQDPJyFWi8lReALNAZrNAZWwtR7lJhj7e7gEaz5jiAAMAA_405_410.png",
            "bg_img_mb": "shopify:\/\/shop_images\/lQDPJyFWi8lReALNAZrNAZWwtR7lJhj7e7gEaz5jiAAMAA_405_410.png",
            "text_main": "Partagez votre moment de bonheur",
            "text_sub": "Suivez-nous sur Facebook et YouTube",
            "img_link": "shopify:\/\/blogs\/blog-heybike"
          }
        }
      },
      "block_order": [
        "16e18420-5cfa-45d6-a2b4-a4157ffc0f22",
        "61279fbb-db0a-4969-b5f8-ca73202edf62"
      ],
      "settings": {
        "top_padding": "large",
        "bottom_padding": "default",
        "title": "Le monde de HEYBIKE",
        "layout": "imgText",
        "enable_slider": false,
        "bottom_line": false
      }
    },
    "e0be29cc-4f32-4503-8012-abbb3949eb80": {
      "type": "banner-with-text",
      "blocks": {
        "template--19143575470395__e0be29cc-4f32-4503-8012-abbb3949eb80-1684744024f2b6438e-0": {
          "type": "row",
          "settings": {
            "image": "shopify:\/\/shop_images\/app720x700.png",
            "image_mb": "shopify:\/\/shop_images\/app720x700.png",
            "layout": "right",
            "title": "Smarttech et APP",
            "text": "<p>Tes superbes balades méritent un journal ! Connectez votre vélo à l'application HEYBIKE, et construisez un compteur kilométrique impressionnant !<\/p>",
            "bottom_logo": "shopify:\/\/shop_images\/icon01.png",
            "logo_url": "shopify:\/\/pages\/trouver-une-affaire",
            "bottom_logo2": "shopify:\/\/shop_images\/icon0.png",
            "logo_url2": "shopify:\/\/pages\/trouver-une-affaire",
            "button_label": "",
            "button_link": "\/",
            "text_align": "text-left",
            "text_center": false,
            "tcl": "#000000",
            "cl": "#000000",
            "bg": "#f3f5f9",
            "btncl": "#ffffff",
            "btnbg": "#000000",
            "btnbd": "#000000"
          }
        }
      },
      "block_order": [
        "template--19143575470395__e0be29cc-4f32-4503-8012-abbb3949eb80-1684744024f2b6438e-0"
      ],
      "settings": {
        "top_padding": "none",
        "bottom_padding": "none",
        "top-offeset": "default",
        "section_style": "heybike",
        "section_width": true,
        "section_cov": false,
        "sec_bg_clr": "#fafafa",
        "snow_effect": false,
        "snow_style": "style1",
        "tfs": 30,
        "tfsm": 210,
        "tff": "ft1",
        "tfw": "700",
        "tlh": 1.2,
        "tmb": 15,
        "tmbm": 10,
        "fs": 14,
        "fsm": 190,
        "fw": "400",
        "lh": 1.6,
        "mb": 15,
        "mbm": 10,
        "btn-size-desk": "btn-md",
        "btn-size-mob": "mob-btn-sm"
      }
    },
    "1633781776086e75a0": {
      "type": "featured-blog",
      "settings": {
        "title": "<b>Heybike Blog<\/b>",
        "subtitle": "En savoir plus sur les connaissances et les informations relatives aux vélos électriques",
        "top-offeset": "default",
        "section_cov": true,
        "sec_bg_clr": "#fafafa",
        "blog": "blog-heybike",
        "img_ratio": "50",
        "post_limit": 3,
        "grid": 3,
        "tablet-grid": 2,
        "mobile-grid": 1,
        "blog_align": "text-center",
        "blog_show_author": false,
        "blog_show_date": true,
        "show_comment": true,
        "show_mini_des": false,
        "show_read_more": false,
        "show_view_all": false,
        "btn-style": "btn",
        "btn-size-desk": "btn-sm",
        "btn-size-mob": "mob-btn-sm"
      }
    },
    "16337817926d98687d": {
      "type": "store-features",
      "blocks": {
        "1561784085337-0": {
          "type": "text_block",
          "settings": {
            "icons": "at-ship-fast",
            "title": "Expédition rapide",
            "text": "<p>Expédition rapide et fiable<\/p>",
            "texturl": ""
          }
        },
        "1561784085337-2": {
          "type": "text_block",
          "settings": {
            "icons": "at-users-l",
            "title": "Soutien rapide",
            "text": "<p>Service de courrier électronique et de téléphone<\/p>",
            "texturl": ""
          }
        },
        "1561784085337-1": {
          "type": "text_block",
          "settings": {
            "icons": "at-shield-check",
            "title": "Essai de 30 jours",
            "text": "<p>Acheter en toute confiance<\/p>",
            "texturl": ""
          }
        }
      },
      "block_order": [
        "1561784085337-0",
        "1561784085337-2",
        "1561784085337-1"
      ],
      "custom_css": [
        ".sec-ttl .h3,div.sec-ttl p {color: #fff;}"
      ],
      "settings": {
        "top_padding": "large",
        "bottom_padding": "extraLarge",
        "top-offeset": "none",
        "section_style": "heybike",
        "section_width": false,
        "section_cov": true,
        "sec_bg_clr": "#232426",
        "hide_mobile": false,
        "title": "Des vélos superbes. Service de qualité supérieure.",
        "subtitle": "Dépasser les attentes grâce à un service à la clientèle hors pair",
        "style": "style1",
        "icon-type": "image",
        "icons_clr": "#ffffff",
        "isz": 59,
        "tcl": "#ffffff",
        "tfs": 24,
        "tfsm": 255,
        "tfw": "600",
        "tlh": 1.2,
        "cl": "#eeeeee",
        "border_sep": "rgba(0,0,0,0)"
      }
    }
  },
  "order": [
    "slideshow",
    "583b741b-600f-49b4-9c12-175b587241ee",
    "6466a547-b260-459b-b173-ee05a2e100ae",
    "8ac0dd31-ebc0-46e2-867c-a7d6e2e0fd90",
    "9097e021-5397-4a21-8d22-e6f121fbda8f",
    "a2d3fa24-4809-40c0-b63d-a720d6b02f2c",
    "e0be29cc-4f32-4503-8012-abbb3949eb80",
    "1633781776086e75a0",
    "16337817926d98687d"
  ]
}
